MANIFEST.in
README.md
setup.py
schemup/__init__.py
schemup/commands.py
schemup/errors.py
schemup/loaders.py
schemup/upgraders.py
schemup/validator.py
schemup.egg-info/PKG-INFO
schemup.egg-info/SOURCES.txt
schemup.egg-info/dependency_links.txt
schemup.egg-info/top_level.txt
schemup/dbs/__init__.py
schemup/dbs/postgres.py
schemup/orms/__init__.py
schemup/orms/dictschema.py
schemup/orms/storm.py