Metadata-Version: 1.0
Name: schemup
Version: 1.0.1
Summary: Database-agnostic schema upgrade tools
Home-page: https://github.com/brendonh/schemup
Author: Brendon Hogger
Author-email: brendonh@gmail.com
License: UNKNOWN
Platform: UNKNOWN
